syngenta_digital_uoms/__init__.py
syngenta_digital_uoms/common/__init__.py
syngenta_digital_uoms/common/adapt_uoms.xlsx
syngenta_digital_uoms/common/vocabulary.py
syngenta_digital_uoms/util/__init__.py
syngenta_digital_uoms/util/converter.py
tests/__init__.py
tests/syngenta_digital_uoms/__init__.py
tests/syngenta_digital_uoms/common/__init__.py
tests/syngenta_digital_uoms/common/test_vocabulary.py
tests/syngenta_digital_uoms/util/__init__.py
tests/syngenta_digital_uoms/util/test_converter.py
syngenta_digital_uoms-0.0.8.dist-info/LICENSE
syngenta_digital_uoms-0.0.8.dist-info/METADATA
syngenta_digital_uoms-0.0.8.dist-info/WHEEL
syngenta_digital_uoms-0.0.8.dist-info/top_level.txt
syngenta_digital_uoms-0.0.8.dist-info/RECORD
