Metadata-Version: 2.1
Name: syngenta-digital-uoms
Version: 0.0.8
Summary: Standardized hub for unit of measure conversions across systems and dimensions.
Home-page: https://github.com/syngenta-digital/package-python-uoms.git
Author: Jeff Payne, Syngenta Digital
Author-email: jeffrey.payne@syngenta.com
Classifier: Intended Audience :: Developers
Classifier: Topic :: Software Development :: Libraries :: Python Modules
Classifier: Programming Language :: Python
Classifier: Programming Language :: Python :: 3
Classifier: Programming Language :: Python :: 3.6
Classifier: Programming Language :: Python :: 3.7
Requires-Python: >=3.0
License-File: LICENSE
Requires-Dist: pandas
Requires-Dist: openpyxl
